{
  "苹果": {
    "iPhone 16 Pro 128GB": 7999,
    "iPhone 16 Pro 256GB": 8999,
    "iPhone 16 Pro 512GB": 10799,
    "iPhone 16 Pro Max 256GB": 9999,
    "iPhone 16 Pro Max 512GB": 11799,
    "iPhone 16 Pro Max 1TB": 13599,
    "iPhone 16 128GB": 5999,
    "iPhone 16 256GB": 6999,
    "iPhone 16 512GB": 8799,
    "iPhone 16 Plus 128GB": 6999,
    "iPhone 16 Plus 256GB": 7999,
    "iPhone 16 Plus 512GB": 9799,
    "iPhone 15 128GB": 4999,
    "iPhone 15 256GB": 5999,
    "iPhone 14 128GB": 4299,
    "iPhone SE 64GB": 3499,
    "iPhone SE 128GB": 3899
  },
  "华为": {
    "华为 Mate 60 Pro 12GB+256GB": 6499,
    "华为 Mate 60 Pro 12GB+512GB": 6999,
    "华为 Mate 60 Pro+ 16GB+512GB": 8999,
    "华为 Mate 60 Pro+ 16GB+1TB": 9999,
    "华为 Mate 50 Pro 8GB+256GB": 6799,
    "华为 Mate 50 Pro 8GB+512GB": 7799,
    "华为 Mate X5 12GB+256GB": 12999,
    "华为 Mate X5 12GB+512GB": 13999,
    "华为 Mate X5 16GB+512GB": 14999,
    "华为 Mate X5 16GB+1TB": 15999,
    "华为 Pocket 2 12GB+256GB": 7499,
    "华为 Pocket 2 12GB+512GB": 7999,
    "华为 P60 8GB+128GB": 3988,
    "华为 P60 8GB+256GB": 4488,
    "华为 P60 Pro 8GB+256GB": 5988,
    "华为 P60 Pro 12GB+512GB": 6988,
    "华为 Nova 12 256GB": 2999,
    "华为 Nova 12 Pro 512GB": 3999,
    "华为畅享 60 8GB+128GB": 1299,
    "华为畅享 60 8GB+256GB": 1499,
    "华为畅享 70 8GB+128GB": 1399,
    "华为畅享 70 8GB+256GB": 1599
  },
  "OPPO": {
    "OPPO Find X9 12GB+256GB": 4399,
    "OPPO Find X9 16GB+256GB": 4699,
    "OPPO Find X9 12GB+512GB": 4999,
    "OPPO Find X9 16GB+512GB": 5299,
    "OPPO Find X9 16GB+1TB": 5799,
    "OPPO Find X9 Pro 12GB+256GB": 5299,
    "OPPO Find X9 Pro 12GB+512GB": 5699,
    "OPPO Find X9 Pro 16GB+512GB": 5999,
    "OPPO Find X9 Pro 16GB+1TB": 6699,
    "OPPO Find N5 12GB+256GB": 8999,
    "OPPO Find N5 16GB+512GB": 9999,
    "OPPO Find N5 16GB+1TB": 10999,
    "OPPO Reno12 8GB+256GB": 2499,
    "OPPO Reno12 12GB+256GB": 2799,
    "OPPO Reno12 Pro 12GB+256GB": 3199,
    "OPPO Reno12 Pro 12GB+512GB": 3499,
    "OPPO A59 6GB+128GB": 1399,
    "OPPO A59 8GB+128GB": 1599,
    "OPPO A79 8GB+256GB": 1799,
    "OPPO A99 12GB+256GB": 1999
  },
  "小米": {
    "小米14 Ultra 12GB+256GB": 5999,
    "小米14 Ultra 16GB+512GB": 6499,
    "小米14 Ultra 16GB+1TB": 6999,
    "小米14 Pro 12GB+256GB": 4999,
    "小米14 Pro 16GB+512GB": 5499,
    "小米14 Pro 16GB+1TB": 5999,
    "小米MIX Fold 4 12GB+256GB": 8999,
    "小米MIX Fold 4 16GB+512GB": 9999,
    "小米MIX Fold 4 16GB+1TB": 10999,
    "小米14 8GB+256GB": 3999,
    "小米14 12GB+256GB": 4299,
    "小米14 16GB+512GB": 4699,
    "小米13 8GB+128GB": 3299,
    "小米13 8GB+256GB": 3599
  },
  "VIVO": {
    "vivo X100 Pro 12GB+256GB": 4999,
    "vivo X100 Pro 16GB+512GB": 5499,
    "vivo X100 Pro 16GB+1TB": 5999,
    "vivo X100 12GB+256GB": 3999,
    "vivo X100 16GB+512GB": 4499,
    "vivo X Fold3 Pro 16GB+512GB": 9999,
    "vivo X Fold3 Pro 16GB+1TB": 10999,
    "vivo X Fold3 12GB+256GB": 6999,
    "vivo X Fold3 16GB+512GB": 7999,
    "vivo S18 12GB+256GB": 2499,
    "vivo S18 16GB+512GB": 2999,
    "vivo S18 Pro 12GB+256GB": 3199,
    "vivo S18 Pro 16GB+512GB": 3499,
    "vivo Y100 8GB+128GB": 1399,
    "vivo Y100 8GB+256GB": 1599,
    "vivo Y78 8GB+128GB": 1299,
    "vivo Y78 8GB+256GB": 1499
  },
  "荣耀": {
    "荣耀Magic6 Pro 12GB+256GB": 5699,
    "荣耀Magic6 Pro 16GB+512GB": 6199,
    "荣耀Magic6 Pro 16GB+1TB": 6699,
    "荣耀Magic6 12GB+256GB": 4399,
    "荣耀Magic6 16GB+512GB": 4699,
    "荣耀Magic V2 16GB+256GB": 8999,
    "荣耀Magic V2 16GB+512GB": 9999,
    "荣耀Magic V2 16GB+1TB": 10999,
    "荣耀V Purse 16GB+256GB": 5999,
    "荣耀V Purse 16GB+512GB": 6599,
    "荣耀100 Pro 12GB+256GB": 3399,
    "荣耀100 Pro 16GB+512GB": 3799,
    "荣耀100 12GB+256GB": 2499,
    "荣耀100 16GB+512GB": 2799,
    "荣耀X50 8GB+128GB": 1399,
    "荣耀X50 8GB+256GB": 1599,
    "荣耀X50 12GB+256GB": 1799,
    "荣耀Play8 6GB+128GB": 999,
    "荣耀Play8 8GB+256GB": 1299
  }
}